Workbook

Sheet Content_data
A1: show_id | B1: type | C1: title | D1: director | E1: cast | F1: country | G1: date_added | H1: release_year | I1: rating | J1: duration | K1: listed_in | L1: description
A2: s1 | B2: Movie | C2: Dick Johnson Is Dead | D2: Kirsten Johnson | F2: United States | G2: 44464 | H2: 2020 | I2: PG-13 | J2: 90 min | K2: Documentaries | L2: As her father nears the end of his life, filmmaker Kirsten Johnson stages his death in inventive and comical ways to help them both face the inevitable.
A3: s2 | B3: TV Show | C3: Blood & Water | E3: Ama Qamata, Khosi Ngema, Gail Mabalane, Thabang Molaba, Dillon Windvogel, Natasha Thahane, Arno Greeff, Xolile Tshabalala, Getmore Sithole, Cindy Mahlangu, Ryle De Morny, Greteli Fincham, Sello Maake Ka-Ncube, Odwa Gwanya, Mekaila Mathys, Sandi Schultz, Duane Williams, Shamilla Miller, Patrick Mofokeng | F3: South Africa | G3: 44463 | H3: 2021 | I3: TV-MA | J3: 2 Seasons | K3: International TV Shows, TV Dramas, TV Mysteries | L3: After crossing paths at a party, a Cape Town teen sets out to prove whether a private-school swimming star is her sister who was abducted at birth.
A4: s3 | B4: TV Show | C4: Ganglands | D4: Julien Leclercq | E4: Sami Bouajila, Tracy Gotoas, Samuel Jouy, Nabiha Akkari, Sofia Lesaffre, Salim Kechiouche, Noureddine Farihi, Geert Van Rampelberg, Bakary Diombera | G4: 44463 | H4: 2021 | I4: TV-MA | J4: 1 Season | K4: Crime TV Shows, International TV Shows, TV Action & Adventure | L4: To protect his family from a powerful drug lord, skilled thief Mehdi and his expert team of robbers are pulled into a violent and deadly turf war.
A5: s4 | B5: TV Show | C5: Jailbirds New Orleans | G5: 44463 | H5: 2021 | I5: TV-MA | J5: 1 Season | K5: Docuseries, Reality TV | L5: Feuds, flirtations and toilet talk go down among the incarcerated women at the Orleans Justice Center in New Orleans on this gritty reality series.
A6: s5 | B6: TV Show | C6: Kota Factory | E6: Mayur More, Jitendra Kumar, Ranjan Raj, Alam Khan, Ahsaas Channa, Revathi Pillai, Urvi Singh, Arun Kumar | F6: India | G6: 44463 | H6: 2021 | I6: TV-MA | J6: 2 Seasons | K6: International TV Shows, Romantic TV Shows, TV Comedies | L6: In a city of coaching centers known to train Indiaâ€™s finest collegiate minds, an earnest but unexceptional student and his friends navigate campus life.
A7: s6 | B7: TV Show | C7: Midnight Mass | D7: Mike Flanagan | E7: Kate Siegel, Zach Gilford, Hamish Linklater, Henry Thomas, Kristin Lehman, Samantha Sloyan, Igby Rigney, Rahul Kohli, Annarah Cymone, Annabeth Gish, Alex Essoe, Rahul Abburi, Matt Biedel, Michael Trucco, Crystal Balint, Louis Oliver | G7: 44463 | H7: 2021 | I7: TV-MA | J7: 1 Season | K7: TV Dramas, TV Horror, TV Mysteries | L7: The arrival of a charismatic young priest brings glorious miracles, ominous mysteries and renewed religious fervor to a dying town desperate to believe.
A8: s7 | B8: Movie | C8: My Little Pony: A New Generation | D8: Robert Cullen, JosÃ© Luis Ucha | E8: Vanessa Hudgens, Kimiko Glenn, James Marsden, Sofia Carson, Liza Koshy, Ken Jeong, Elizabeth Perkins, Jane Krakowski, Michael McKean, Phil LaMarr | G8: 44463 | H8: 2021 | I8: PG | J8: 91 min | K8: Children & Family Movies | L8: Equestria's divided. But a bright-eyed hero believes Earth Ponies, Pegasi and Unicorns should be pals â€” and, hoof to heart, sheâ€™s determined to prove it.
A9: s8 | B9: Movie | C9: Sankofa | D9: Haile Gerima | E9: Kofi Ghanaba, Oyafunmike Ogunlano, Alexandra Duah, Nick Medley, Mutabaruka, Afemo Omilami, Reggie Carter, Mzuri | F9: United States, Ghana, Burkina Faso, United Kingdom, Germany, Ethiopia | G9: 44463 | H9: 1993 | I9: TV-MA | J9: 125 min | K9: Dramas, Independent Movies, International Movies | L9: On a photo shoot in Ghana, an American model slips back in time, becomes enslaved on a plantation and bears witness to the agony of her ancestral past.
A10: s9 | B10: TV Show | C10: The Great British Baking Show | D10: Andy Devonshire | E10: Mel Giedroyc, Sue Perkins, Mary Berry, Paul Hollywood | F10: United Kingdom | G10: 44463 | H10: 2021 | I10: TV-14 | J10: 9 Seasons | K10: British TV Shows, Reality TV | L10: A talented batch of amateur bakers face off in a 10-week competition, whipping up their best dishes in the hopes of being named the U.K.'s best.
A11: s10 | B11: Movie | C11: The Starling | D11: Theodore Melfi | E11: Melissa McCarthy, Chris O'Dowd, Kevin Kline, Timothy Olyphant, Daveed Diggs, Skyler Gisondo, Laura Harrier, Rosalind Chao, Kimberly Quinn, Loretta Devine, Ravi Kapoor | F11: United States | G11: 44463 | H11: 2021 | I11: PG-13 | J11: 104 min | K11: Comedies, Dramas | L11: A woman adjusting to life after a loss contends with a feisty bird that's taken over her garden â€” and a husband who's struggling to find a way forward.
A12: s11 | B12: TV Show | C12: Vendetta: Truth, Lies and The Mafia | G12: 44463 | H12: 2021 | I12: TV-MA | J12: 1 Season | K12: Crime TV Shows, Docuseries, International TV Shows | L12: Sicily boasts a bold "Anti-Mafia" coalition. But what happens when those trying to bring down organized crime are accused of being criminals themselves?
A13: s12 | B13: TV Show | C13: Bangkok Breaking | D13: Kongkiat Komesiri | E13: Sukollawat Kanarot, Sushar Manaying, Pavarit Mongkolpisit, Sahajak Boonthanakit, Suthipongse Thatphithakkul, Bhasaworn Bawronkirati, Daweerit Chullasapya, Waratthaya Wongchayaporn, Kittiphoom Wongpentak, Abhicha Thanachanun, Nophand Boonyai, Kittipong Khamsat, Arisara Wongchalee, Jaytiya Naiwattanakul, Pantipa Arunwattanachai, Panupan Jantanawong, Kungtap Saelim, Phumphat Chartsuriyakiat, Issara Veranitinunt, Keerati Sivakuae, Panjai Sirisuwan, Supranee Charoenpol, Suda Chuenban, Visaka Banhansupavat, Pitchatorn Santinatornkul | G13: 44462 | H13: 2021 | I13: TV-MA | J13: 1 Season | K13: Crime TV Shows, International TV Shows, TV Action & Adventure | L13: Struggling to earn a living in Bangkok, a man joins an emergency rescue service and realizes he must unravel a citywide conspiracy.
A14: s13 | B14: Movie | C14: Je Suis Karl | D14: Christian Schwochow | E14: Luna Wedler, Jannis NiewÃ¶hner, Milan Peschel, Edin HasanoviÄ‡, Anna FialovÃ¡, Marlon Boess, Victor Boccard, Fleur Geffrier, Aziz Dyab, MÃ©lanie FouchÃ©, Elizaveta MaximovÃ¡ | F14: Germany, Czech Republic | G14: 44462 | H14: 2021 | I14: TV-MA | J14: 127 min | K14: Dramas, International Movies | L14: After most of her family is murdered in a terrorist bombing, a young woman is unknowingly lured into joining the very group that killed them.
A15: s14 | B15: Movie | C15: Confessions of an Invisible Girl | D15: Bruno Garotti | E15: Klara Castanho, Lucca Picon, JÃºlia Gomes, Marcus Bessa, Kiria Malheiros, Fernanda Concon, Gabriel Lima, Caio Cabral, Leonardo Cidade, Jade Cardozo | G15: 44461 | H15: 2021 | I15: TV-PG | J15: 91 min | K15: Children & Family Movies, Comedies | L15: When the clever but socially-awkward TetÃª joins a new school, she'll do anything to fit in. But the queen bee among her classmates has other ideas.
A16: s15 | B16: TV Show | C16: Crime Stories: India Detectives | G16: 44461 | H16: 2021 | I16: TV-MA | J16: 1 Season | K16: British TV Shows, Crime TV Shows, Docuseries | L16: Cameras following Bengaluru police on the job offer a rare glimpse into the complex and challenging inner workings of four major crime investigations.
A17: s16 | B17: TV Show | C17: Dear White People | E17: Logan Browning, Brandon P. Bell, DeRon Horton, Antoinette Robertson, John Patrick Amedori, Ashley Blaine Featherson, Marque Richardson, Giancarlo Esposito | F17: United States | G17: 44461 | H17: 2021 | I17: TV-MA | J17: 4 Seasons | K17: TV Comedies, TV Dramas | L17: Students of color navigate the daily slights and slippery politics of life at an Ivy League college that's not nearly as "post-racial" as it thinks.
A18: s17 | B18: Movie | C18: Europe's Most Dangerous Man: Otto Skorzeny in Spain | D18: Pedro de Echave GarcÃ­a, Pablo AzorÃ­n Williams | G18: 44461 | H18: 2020 | I18: TV-MA | J18: 67 min | K18: Documentaries, International Movies | L18: Declassified documents reveal the post-WWII life of Otto Skorzeny, a close Hitler ally who escaped to Spain and became an adviser to world presidents.
A19: s18 | B19: TV Show | C19: Falsa identidad | E19: Luis Ernesto Franco, Camila Sodi, Sergio Goyri, Samadhi Zendejas, Eduardo YÃ¡Ã±ez, Sonya Smith, Alejandro Camacho, Azela Robinson, Uriel del Toro, GÃ©raldine BazÃ¡n, Gabriela Roel, Marcus Ornellas | F19: Mexico | G19: 44461 | H19: 2020 | I19: TV-MA | J19: 2 Seasons | K19: Crime TV Shows, Spanish-Language TV Shows, TV Dramas | L19: Strangers Diego and Isabel flee their home in Mexico and pretend to be a married couple to escape his drug-dealing enemies and her abusive husband.
A20: s19 | B20: Movie | C20: Intrusion | D20: Adam Salky | E20: Freida Pinto, Logan Marshall-Green, Robert John Burke, Megan Elisabeth Kelly, Sarah Minnich, Hayes Hargrove, Mark Sivertsen, Brandon Fierro, Antonio Valles, Clint Obenchain | G20: 44461 | H20: 2021 | I20: TV-14 | J20: 94 min | K20: Thrillers | L20: After a deadly home invasion at a coupleâ€™s new dream house, the traumatized wife searches for answers â€” and learns the real danger is just beginning.
A21: s20 | B21: TV Show | C21: Jaguar | E21: Blanca SuÃ¡rez, IvÃ¡n Marcos, Ã“scar Casas, AdriÃ¡n Lastra, Francesc Garrido, Stefan Weinert, Julia MÃ¶ller, Alicia Chojnowski | G21: 44461 | H21: 2021 | I21: TV-MA | J21: 1 Season | K21: International TV Shows, Spanish-Language TV Shows, TV Action & Adventure | L21: In the 1960s, a Holocaust survivor joins a group of self-trained spies who seek justice against Nazis fleeing to Spain to hide after WWII.
A22: s21 | B22: TV Show | C22: Monsters Inside: The 24 Faces of Billy Milligan | D22: Olivier Megaton | G22: 44461 | H22: 2021 | I22: TV-14 | J22: 1 Season | K22: Crime TV Shows, Docuseries, International TV Shows | L22: In the late 1970s, an accused serial rapist claims multiple personalities control his behavior, setting off a legal odyssey that captivates America.
A23: s22 | B23: TV Show | C23: Resurrection: Ertugrul | E23: Engin Altan DÃ¼zyatan, Serdar GÃ¶khan, HÃ¼lya Darcan, Kaan TaÅŸaner, Esra BilgiÃ§, Osman Soykut, Serdar Deniz, Cengiz CoÅŸkun, Reshad Strik, Hande SubaÅŸÄ± | F23: Turkey | G23: 44461 | H23: 2018 | I23: TV-14 | J23: 5 Seasons | K23: International TV Shows, TV Action & Adventure, TV Dramas | L23: When a good deed unwittingly endangers his clan, a 13th-century Turkish warrior agrees to fight a sultan's enemies in exchange for new tribal land.
A24: s23 | B24: Movie | C24: Avvai Shanmughi | D24: K.S. Ravikumar | E24: Kamal Hassan, Meena, Gemini Ganesan, Heera Rajgopal, Nassar, S.P. Balasubrahmanyam | G24: 44460 | H24: 1996 | I24: TV-PG | J24: 161 min | K24: Comedies, International Movies | L24: Newly divorced and denied visitation rights with his daughter, a doting father disguises himself as a gray-haired nanny in order to spend time with her.
A25: s24 | B25: Movie | C25: Go! Go! Cory Carson: Chrissy Takes the Wheel | D25: Alex Woo, Stanley Moore | E25: Maisie Benson, Paul Killam, Kerry Gudjohnsen, AC Lim | G25: 44460 | H25: 2021 | I25: TV-Y | J25: 61 min | K25: Children & Family Movies | L25: From arcade games to sled days and hiccup cures, Cory Carsonâ€™s curious little sister Chrissy speeds off on her own for fun and adventure all over town!
A26: s25 | B26: Movie | C26: Jeans | D26: S. Shankar | E26: Prashanth, Aishwarya Rai Bachchan, Sri Lakshmi, Nassar | F26: India | G26: 44460 | H26: 1998 | I26: TV-14 | J26: 166 min | K26: Comedies, International Movies, Romantic Movies | L26: When the father of the man she loves insists that his twin sons marry twin sisters, a woman creates an alter ego that might be a bit too convincing.
A27: s26 | B27: TV Show | C27: Love on the Spectrum | E27: Brooke Satchwell | F27: Australia | G27: 44460 | H27: 2021 | I27: TV-14 | J27: 2 Seasons | K27: Docuseries, International TV Shows, Reality TV | L27: Finding love can be hard for anyone. For young adults on the autism spectrum, exploring the unpredictable world of dating is even more complicated.
A28: s27 | B28: Movie | C28: Minsara Kanavu | D28: Rajiv Menon | E28: Arvind Swamy, Kajol, Prabhu Deva, Nassar, S.P. Balasubrahmanyam, Girish Karnad | G28: 44460 | H28: 1997 | I28: TV-PG | J28: 147 min | K28: Comedies, International Movies, Music & Musicals | L28: A tangled love triangle ensues when a man falls for a woman studying to become a nun â€” and she falls for the friend he enlists to help him pursue her.
A29: s28 | B29: Movie | C29: Grown Ups | D29: Dennis Dugan | E29: Adam Sandler, Kevin James, Chris Rock, David Spade, Rob Schneider, Salma Hayek, Maria Bello, Maya Rudolph, Colin Quinn, Tim Meadows, Joyce Van Patten | F29: United States | G29: 44459 | H29: 2010 | I29: PG-13 | J29: 103 min | K29: Comedies | L29: Mourning the loss of their beloved junior high basketball coach, five middle-aged pals reunite at a lake house and rediscover the joys of being a kid.
A30: s29 | B30: Movie | C30: Dark Skies | D30: Scott Stewart | E30: Keri Russell, Josh Hamilton, J.K. Simmons, Dakota Goyo, Kadan Rockett, L.J. Benet, Rich Hutchman, Myndy Crist, Annie Thurman, Jake Brennan | F30: United States | G30: 44458 | H30: 2013 | I30: PG-13 | J30: 97 min | K30: Horror Movies, Sci-Fi & Fantasy | L30: A familyâ€™s idyllic suburban life shatters when an alien force invades their home, and as they struggle to convince others of the deadly threat.
A31: s30 | B31: Movie | C31: Paranoia | D31: Robert Luketic | E31: Liam Hemsworth, Gary Oldman, Amber Heard, Harrison Ford, Lucas Till, Embeth Davidtz, Julian McMahon, Josh Holloway, Richard Dreyfuss, Angela Sarafyan | F31: United States, India, France | G31: 44458 | H31: 2013 | I31: PG-13 | J31: 106 min | K31: Thrillers | L31: Blackmailed by his company's CEO, a low-level employee finds himself forced to spy on the boss's rival and former mentor.
A32: s31 | B32: Movie | C32: Ankahi Kahaniya | D32: Ashwiny Iyer Tiwari, Abhishek Chaubey, Saket Chaudhary | E32: Abhishek Banerjee, Rinku Rajguru, Delzad Hiwale, Kunal Kapoor, Zoya Hussain, Nikhil Dwivedi, Palomi Ghosh | G32: 44456 | H32: 2021 | I32: TV-14 | J32: 111 min | K32: Dramas, Independent Movies, International Movies | L32: As big city life buzzes around them, lonely souls discover surprising sources of connection and companionship in three tales of love, loss and longing.
A33: s32 | B33: TV Show | C33: Chicago Party Aunt | E33: Lauren Ash, Rory O'Malley, RuPaul Charles, Jill Talley, Ike Barinholtz, Jon Barinholtz, Matthew Craig, Bob Odenkirk, Mike Hagerty, Katie Rich, Chris Witaske | G33: 44456 | H33: 2021 | I33: TV-MA | J33: 1 Season | K33: TV Comedies | L33: Chicago Party Aunt Diane is an idolized troublemaker with a talent for avoiding adulthood â€” and a soft spot for her soul-searching nephew.
A34: s33 | B34: TV Show | C34: Sex Education | E34: Asa Butterfield, Gillian Anderson, Ncuti Gatwa, Emma Mackey, Connor Swindells, Kedar Williams-Stirling, Alistair Petrie | F34: United Kingdom | G34: 44456 | H34: 2020 | I34: TV-MA | J34: 3 Seasons | K34: British TV Shows, International TV Shows, TV Comedies | L34: Insecure Otis has all the answers when it comes to sex advice, thanks to his therapist mom. So rebel Maeve proposes a school sex-therapy clinic.
A35: s34 | B35: TV Show | C35: Squid Game | E35: Lee Jung-jae, Park Hae-soo, Wi Ha-jun, Oh Young-soo, Jung Ho-yeon, Heo Sung-tae, Kim Joo-ryoung, Tripathi Anupam, You Seong-joo, Lee You-mi | G35: 44456 | H35: 2021 | I35: TV-MA | J35: 1 Season | K35: International TV Shows, TV Dramas, TV Thrillers | L35: Hundreds of cash-strapped players accept a strange invitation to compete in children's games. Inside, a tempting prize awaits â€” with deadly high stakes.
A36: s35 | B36: TV Show | C36: Tayo and Little Wizards | E36: Dami Lee, Jason Lee, Bommie Catherine Han, Jennifer Waescher, Nancy Kim | G36: 44456 | H36: 2020 | I36: TV-Y7 | J36: 1 Season | K36: Kids' TV | L36: Tayo speeds into an adventure when his friends get kidnapped by evil magicians invading their city in search of a magical gemstone.
A37: s36 | B37: Movie | C37: The Father Who Moves Mountains | D37: Daniel Sandu | E37: Adrian Titieni, Elena Purea, Judith State, Valeriu AndriuÈ›Äƒ, Tudor Smoleanu, Virgil Aioanei, Radu Botar, Petronela Grigorescu, Bogdan Nechifor, Cristian Bota | G37: 44456 | H37: 2021 | I37: TV-MA | J37: 110 min | K37: Dramas, International Movies, Thrillers | L37: When his son goes missing during a snowy hike in the mountains, a retired intelligence officer will stop at nothing â€” and risk everything â€” to find him.
A38: s37 | B38: Movie | C38: The Stronghold | D38: CÃ©dric Jimenez | E38: Gilles Lellouche, Karim Leklou, FranÃ§ois Civil, AdÃ¨le Exarchopoulos, Kenza Fortas, Cyril Lecomte, MichaÃ«l Abiteboul, Idir Azougli, Vincent Darmuzey, Jean-Yves Berteloot | G38: 44456 | H38: 2021 | I38: TV-MA | J38: 105 min | K38: Action & Adventure, Dramas, International Movies | L38: Tired of the small-time grind, three Marseille cops get a chance to bust a major drug network. But lines blur when a key informant makes a big ask.
A39: s38 | B39: TV Show | C39: Angry Birds | E39: Antti PÃ¤Ã¤kkÃ¶nen, HeljÃ¤ Heikkinen, Lynne Guaglione, Pasi Ruohonen, Rauno Ahonen | F39: Finland | G39: 44455 | H39: 2018 | I39: TV-Y7 | J39: 1 Season | K39: Kids' TV, TV Comedies | L39: Birds Red, Chuck and their feathered friends have lots of adventures while guarding eggs in their nest that pesky pigs keep trying to steal.
A40: s39 | B40: Movie | C40: Birth of the Dragon | D40: George Nolfi | E40: Billy Magnussen, Ron Yuan, Qu Jingjing, Terry Chen, Vanness Wu, Jin Xing, Philip Ng, Xia Yu, Yu Xia | F40: China, Canada, United States | G40: 44455 | H40: 2017 | I40: PG-13 | J40: 96 min | K40: Action & Adventure, Dramas | L40: A young Bruce Lee angers kung fu traditionalists by teaching outsiders, leading to a showdown with a Shaolin master in this film based on real events.
A41: s40 | B41: TV Show | C41: Chhota Bheem | E41: Vatsal Dubey, Julie Tejwani, Rupa Bhimani, Jigna Bhardwaj, Rajesh Kava, Mousam, Swapnil | F41: India | G41: 44455 | H41: 2021 | I41: TV-Y7 | J41: 3 Seasons | K41: Kids' TV | L41: A brave, energetic little boy with superhuman powers leads his friends on exciting adventures to guard their fellow Dholakpur villagers from evil.
A42: s41 | B42: TV Show | C42: He-Man and the Masters of the Universe | E42: Yuri Lowenthal, Kimberly Brooks, Antony Del Rio, Trevor Devall, Ben Diskin, Grey Griffin, David Kaye, Tom Kenny, Judy Alice Lee, Roger Craig Smith, Fred Tatasciore | F42: United States | G42: 44455 | H42: 2021 | I42: TV-Y7 | J42: 1 Season | K42: Kids' TV, TV Sci-Fi & Fantasy | L42: Mighty teen Adam and his heroic squad of misfits discover the legendary power of Grayskull â€” and their destiny to defend Eternia from sinister Skeletor.
A43: s42 | B43: Movie | C43: Jaws | D43: Steven Spielberg | E43: Roy Scheider, Robert Shaw, Richard Dreyfuss, Lorraine Gary, Murray Hamilton, Carl Gottlieb, Jeffrey Kramer, Susan Backlinie, Jonathan Filley, Ted Grossman | F43: United States | G43: 44455 | H43: 1975 | I43: PG | J43: 124 min | K43: Action & Adventure, Classic Movies, Dramas | L43: When an insatiable great white shark terrorizes Amity Island, a police chief, an oceanographer and a grizzled shark hunter seek to destroy the beast.
A44: s43 | B44: Movie | C44: Jaws 2 | D44: Jeannot Szwarc | E44: Roy Scheider, Lorraine Gary, Murray Hamilton, Joseph Mascolo, Jeffrey Kramer, Collin Wilcox Paxton, Ann Dusenberry, Mark Gruner, Barry Coe, Susan French | F44: United States | G44: 44455 | H44: 1978 | I44: PG | J44: 116 min | K44: Dramas, Horror Movies, Thrillers | L44: Four years after the last deadly shark attacks, police chief Martin Brody fights to protect Amity Island from another killer great white.
A45: s44 | B45: Movie | C45: Jaws 3 | D45: Joe Alves | E45: Dennis Quaid, Bess Armstrong, Simon MacCorkindale, Louis Gossett Jr., John Putch, Lea Thompson, P.H. Moriarty, Dan Blasko, Liz Morris, Lisa Maurer | F45: United States | G45: 44455 | H45: 1983 | I45: PG | J45: 98 min | K45: Action & Adventure, Horror Movies, Thrillers | L45: After the staff of a marine theme park try to capture a young great white shark, they discover its mother has invaded the enclosure and is out for blood.
A46: s45 | B46: Movie | C46: Jaws: The Revenge | D46: Joseph Sargent | E46: Lorraine Gary, Lance Guest, Mario Van Peebles, Karen Young, Michael Caine, Judith Barsi, Mitchell Anderson, Lynn Whitfield | F46: United States | G46: 44455 | H46: 1987 | I46: PG-13 | J46: 91 min | K46: Action & Adventure, Horror Movies, Thrillers | L46: After another deadly shark attack, Ellen Brody has had enough of Amity Island and moves to the Caribbean â€“ but a great white shark follows her there.
A47: s46 | B47: Movie | C47: My Heroes Were Cowboys | D47: Tyler Greco | G47: 44455 | H47: 2021 | I47: PG | J47: 23 min | K47: Documentaries | L47: Robin Wiltshire's painful childhood was rescued by Westerns. Now he lives on the frontier of his dreams, training the horses he loves for the big screen.
A48: s47 | B48: Movie | C48: Safe House | D48: Daniel Espinosa | E48: Denzel Washington, Ryan Reynolds, Vera Farmiga, Brendan Gleeson, Sam Shepard, RubÃ©n Blades, Nora Arnezeder, Robert Patrick, Liam Cunningham, Joel Kinnaman | F48: South Africa, United States, Japan | G48: 44455 | H48: 2012 | I48: R | J48: 115 min | K48: Action & Adventure | L48: Young CIA operative Matt Weston must get a dangerous criminal out of an agency safe house that's come under attack and get him to a securer location.
A49: s48 | B49: TV Show | C49: The Smart Money Woman | D49: Bunmi Ajakaiye | E49: Osas Ighodaro, Ini Dima-Okojie, Kemi Lala Akindoju, Toni Tones, Ebenezer Eno, Eso Okolocha DIke, Patrick Diabuah, Karibi Fubara, Temisan Emmanuel, Timini Egbuson | G49: 44455 | H49: 2020 | I49: TV-MA | J49: 1 Season | K49: International TV Shows, Romantic TV Shows, TV Comedies | L49: Five glamorous millennials strive for success as they juggle careers, finances, love and friendships. Based on Arese Ugwu's 2016 best-selling novel.
A50: s49 | B50: Movie | C50: Training Day | D50: Antoine Fuqua | E50: Denzel Washington, Ethan Hawke, Scott Glenn, Tom Berenger, Harris Yulin, Raymond J. Barry, Cliff Curtis, Dr. Dre, Snoop Dogg, Macy Gray, Eva Mendes | F50: United States | G50: 44455 | H50: 2001 | I50: R | J50: 122 min | K50: Dramas, Thrillers | L50: A rookie cop with one day to prove himself to a veteran LAPD narcotics officer receives a crash course in his mentor's questionable brand of justice.
A51: s50 | B51: TV Show | C51: Castle and Castle | E51: Richard Mofe-Damijo, Dakore Akande, Bimbo Manuel, Blossom Chukwujekwu, Deyemi Okanlawon, Etim Effiong, Denola Grey, Duke Akintola, Eku Edewor, Ade Laoye, Anee Icha, Kevin Ushi, Jude Chukwuka, Amanda Afolabi | F51: Nigeria | G51: 44454 | H51: 2021 | I51: TV-MA | J51: 2 Seasons | K51: International TV Shows, TV Dramas | L51: A pair of high-powered, successful lawyers find themselves defending opposite interests of the justice system, causing a strain on their happy marriage.
A52: s51 | B52: TV Show | C52: Dharmakshetra | E52: Kashmira Irani, Chandan Anand, Dinesh Mehta, Ankit Arora, Pushkar Goggiaa, Anjali Rana, Aarya DharmChand Kumar, Amit Behl, Maleeka Ghai | F52: India | G52: 44454 | H52: 2014 | I52: TV-PG | J52: 1 Season | K52: International TV Shows, TV Dramas, TV Sci-Fi & Fantasy | L52: After the ancient Great War, the god Chitragupta oversees a trial to determine who were the battle's true heroes and villains.
A53: s52 | B53: Movie | C53: InuYasha the Movie 2: The Castle Beyond the Looking Glass | D53: Toshiya Shinohara | E53: Kappei Yamaguchi, Satsuki Yukino, Mieko Harada, Koji Tsujitani, Houko Kuwashima, Kumiko Watanabe, Noriko Hidaka, Kenichi Ogata, Toshiyuki Morikawa, Izumi Ogami | F53: Japan | G53: 44454 | H53: 2002 | I53: TV-14 | J53: 99 min | K53: Action & Adventure, Anime Features, International Movies | L53: With their biggest foe seemingly defeated, InuYasha and his friends return to everyday life. But the peace is soon shattered by an emerging new enemy.
A54: s53 | B54: Movie | C54: InuYasha the Movie 3: Swords of an Honorable Ruler | D54: Toshiya Shinohara | E54: Kappei Yamaguchi, Satsuki Yukino, Koji Tsujitani, Houko Kuwashima, Kumiko Watanabe, Ken Narita, Akio Otsuka, Kikuko Inoue | F54: Japan | G54: 44454 | H54: 2003 | I54: TV-14 | J54: 99 min | K54: Action & Adventure, Anime Features, International Movies | L54: The Great Dog Demon beaqueathed one of the Three Swords of the Fang to each of his two sons. Now the evil power of the third sword has been awakened.
A55: s54 | B55: Movie | C55: InuYasha the Movie 4: Fire on the Mystic Island | D55: Toshiya Shinohara | E55: Kappei Yamaguchi, Satsuki Yukino, Koji Tsujitani, Houko Kuwashima, Kumiko Watanabe, Noriko Hidaka, Ken Narita, Cho, Mamiko Noto, Nobutoshi Canna | F55: Japan | G55: 44454 | H55: 2004 | I55: TV-PG | J55: 88 min | K55: Action & Adventure, Anime Features, International Movies | L55: Ai, a young half-demon who has escaped from Horai Island to try to help her people, returns with potential saviors InuYasha, Sesshomaru and Kikyo.
A56: s55 | B56: Movie | C56: InuYasha the Movie: Affections Touching Across Time | D56: Toshiya Shinohara | E56: Kappei Yamaguchi, Satsuki Yukino, Koji Tsujitani, Houko Kuwashima, Kumiko Watanabe, Kenichi Ogata, Noriko Hidaka, Hisako Kyoda, Ken Narita, Tomokazu Seki | F56: Japan | G56: 44454 | H56: 2001 | I56: TV-PG | J56: 100 min | K56: Action & Adventure, Anime Features, International Movies | L56: A powerful demon has been sealed away for 200 years. But when the demon's son is awakened, the fate of the world is in jeopardy.
A57: s56 | B57: TV Show | C57: Nailed It | E57: Nicole Byer, Jacques Torres | F57: United States | G57: 44454 | H57: 2021 | I57: TV-PG | J57: 6 Seasons | K57: Reality TV | L57: Home bakers with a terrible track record take a crack at re-creating edible masterpieces for a $10,000 prize. It's part reality contest, part hot mess.
A58: s57 | B58: Movie | C58: Naruto Shippuden the Movie: Blood Prison | D58: Masahiko Murata | E58: Junko Takeuchi, Chie Nakamura, Rikiya Koyama, Kazuhiko Inoue, Masaki Terasoma, Mie Sonozaki, Yuichi Nakamura, Kengo Kawanishi, Kosei Hirota, Masako Katsuki | F58: Japan | G58: 44454 | H58: 2011 | I58: TV-14 | J58: 102 min | K58: Action & Adventure, Anime Features, International Movies | L58: Mistakenly accused of an attack on the Fourth Raikage, ninja Naruto is imprisoned in the impenetrable Hozuki Castle and his powers are sealed.
A59: s58 | B59: Movie | C59: Naruto ShippÃ»den the Movie: Bonds | D59: Hajime Kamegaki | E59: Junko Takeuchi, Chie Nakamura, Noriaki Sugiyama, Unsho Ishizuka, Motoko Kumai, Kazuhiko Inoue, Rikiya Koyama, Showtaro Morikubo, Nana Mizuki, Satoshi Hino, Shinji Kawada | F59: Japan | G59: 44454 | H59: 2008 | I59: TV-PG | J59: 93 min | K59: Action & Adventure, Anime Features, International Movies | L59: When strange ninjas ambush the village of Konohagakure, it's up to adolescent ninja Naruto and his long-missing pal, Sasuke, to save the planet.
A60: s59 | B60: Movie | C60: Naruto ShippÃ»den the Movie: The Will of Fire | D60: Masahiko Murata | E60: Junko Takeuchi, Chie Nakamura, Kazuhiko Inoue, Satoshi Hino, Showtaro Morikubo, Kentaro Ito, Ryoka Yuzuki, Kohsuke Toriumi, Nana Mizuki, Shinji Kawada, Yoichi Masukawa, Koichi Tochika, Yukari Tamura | F60: Japan | G60: 44454 | H60: 2009 | I60: TV-PG | J60: 96 min | K60: Action & Adventure, Anime Features, International Movies | L60: When four out of five ninja villages are destroyed, the leader of the one spared tries to find the true culprit and protect his land.
A61: s60 | B61: Movie | C61: Naruto Shippuden: The Movie | D61: Hajime Kamegaki | E61: Junko Takeuchi, Chie Nakamura, Yoichi Masukawa, Koichi Tochika, Ayumi Fujimura, Keisuke Oda, Daisuke Kishio, Fumiko Orikasa, Hidetoshi Nakamura, Tetsuya Kakihara, Kisho Taniyama, Miyuki Sawashiro, Katsuyuki Konishi, Masako Katsuki, Keiko Nemoto, Masashi Ebara, Kazuhiko Inoue, Showtaro Morikubo, Romi Park, Daisuke Ono, Seizo Kato | F61: Japan | G61: 44454 | H61: 2007 | I61: TV-PG | J61: 95 min | K61: Action & Adventure, Anime Features, International Movies | L61: The adventures of adolescent ninja Naruto Uzumaki continue as he's tasked with protecting a priestess from a demon â€“ but to do so, he must die.
A62: s61 | B62: Movie | C62: Naruto Shippuden: The Movie: The Lost Tower | D62: Masahiko Murata | E62: Junko Takeuchi, Chie Nakamura, Satoshi Hino, Rikiya Koyama, Nobuaki Fukuda, Kenji Hamada, Keiko Nemoto, Saori Hayami, Yumi Toma, Yuko Kobayashi, Fujiko Takimoto, Mutsumi Tamura, Mayuki Makiguchi, Toshiyuki Morikawa | F62: Japan | G62: 44454 | H62: 2010 | I62: TV-14 | J62: 85 min | K62: Action & Adventure, Anime Features, International Movies | L62: When Naruto is sent to recover a missing nin, the rogue manages to send him 20 years into the past, where he unites with his father to battle evil.
A63: s62 | B63: Movie | C63: Naruto the Movie 2: Legend of the Stone of Gelel | D63: Hirotsugu Kawasaki | E63: Junko Takeuchi, Gamon Kaai, Chie Nakamura, Showtaro Morikubo, Akira Ishida, Yasuyuki Kase, Urara Takano, Sachiko Kojima, Houko Kuwashima, Takako Honda | F63: Japan | G63: 44454 | H63: 2005 | I63: TV-PG | J63: 97 min | K63: Action & Adventure, Anime Features, International Movies | L63: While on a mission to return a missing pet, Naruto and two fellow ninjas are ambushed by brutal knights led by the enigmatic Temujin.
A64: s63 | B64: Movie | C64: Naruto the Movie 3: Guardians of the Crescent Moon Kingdom | D64: Toshiyuki Tsuru | E64: Junko Takeuchi, Chie Nakamura, Yoichi Masukawa, Kazuhiko Inoue, Akio Otsuka, Kyousuke Ikeda, Marika Hayashi, Umeji Sasaki, Masashi Sugawara, Hisao Egawa | F64: Japan | G64: 44454 | H64: 2006 | I64: TV-PG | J64: 95 min | K64: Action & Adventure, Anime Features, International Movies | L64: Exuberant ninja Naruto teams up with his pals Sakura and Kakashi to escort Prince Michiru and his son, Hikaru, to the Crescent Moon kingdom.
A65: s64 | B65: Movie | C65: Naruto the Movie: Ninja Clash in the Land of Snow | D65: Tensai Okamura | E65: Junko Takeuchi, Noriaki Sugiyama, Chie Nakamura, Kazuhiko Inoue, Yuhko Kaida, Tsutomu Isobe, Hirotaka Suzuoki, Jun Karasawa, Harii Kaneko, Ikuo Nishikawa | F65: Japan | G65: 44454 | H65: 2004 | I65: TV-PG | J65: 83 min | K65: Action & Adventure, Anime Features, International Movies | L65: Naruto, Sasuke and Sakura learn they'll be protecting an actress from being hurt while making her next film, but it turns out she's a princess.
A66: s65 | B66: Movie | C66: Nightbooks | D66: David Yarovesky | E66: Winslow Fegley, Lidya Jewett, Krysten Ritter | G66: 44454 | H66: 2021 | I66: TV-PG | J66: 103 min | K66: Children & Family Movies | L66: Scary story fan Alex must tell a spine-tingling tale every night â€” or stay trapped with his new friend in a wicked witch's magical apartment forever.
A67: s66 | B67: TV Show | C67: Numberblocks | E67: Beth Chalmers, David Holt, Marcel McCalla, Teresa Gallagher | F67: United Kingdom | G67: 44454 | H67: 2021 | I67: TV-Y | J67: 6 Seasons | K67: Kids' TV | L67: In a place called Numberland, math adds up to tons of fun when a group of cheerful blocks work, play and sing together.
A68: s67 | B68: TV Show | C68: Raja Rasoi Aur Anya Kahaniyan | F68: India | G68: 44454 | H68: 2014 | I68: TV-G | J68: 1 Season | K68: Docuseries, International TV Shows | L68: Explore the history and flavors of regional Indian cuisine, from traditional Kashmiri feasts to the vegetarian dishes of Gujarat.
A69: s68 | B69: TV Show | C69: Saved by the Bell | E69: Mark-Paul Gosselaar, Tiffani Thiessen, Mario Lopez, Lark Voorhies, Elizabeth Berkley, Dustin Diamond, Dennis Haskins | F69: United States | G69: 44454 | H69: 1994 | I69: TV-PG | J69: 9 Seasons | K69: Kids' TV, TV Comedies | L69: From middle school to college, best friends Zack, Kelly, Slater, Jessie, Screech and Lisa take on the highs and lows of life together in this hit series.
A70: s69 | B70: Movie | C70: Schumacher | D70: Hanns-Bruno KammertÃ¶ns, Vanessa NÃ¶cker, Michael Wech | E70: Michael Schumacher | G70: 44454 | H70: 2021 | I70: TV-14 | J70: 113 min | K70: Documentaries, International Movies, Sports Movies | L70: Through exclusive interviews and archival footage, this documentary traces an intimate portrait of seven-time Formula 1 champion Michael Schumacher.
A71: s70 | B71: TV Show | C71: Stories by Rabindranath Tagore | F71: India | G71: 44454 | H71: 2015 | I71: TV-PG | J71: 1 Season | K71: International TV Shows, TV Dramas | L71: The writings of Nobel Prize winner Rabindranath Tagore come to life in this collection of tales set in early-20th-century Bengal.
A72: s71 | B72: TV Show | C72: Too Hot To Handle: Latino | E72: ItatÃ­ Cantoral | G72: 44454 | H72: 2021 | I72: TV-MA | J72: 1 Season | K72: International TV Shows, Reality TV, Romantic TV Shows | L72: On this reality show, singles from Latin America and Spain are challenged to give up sex. But here, abstinence comes with a silver lining: US$100,000.
A73: s72 | B73: Movie | C73: A StoryBots Space Adventure | D73: David A. Vargas | E73: Evan Spiridellis, Erin Fitzgerald, Jeff Gill, Fred Tatasciore, Evan Michael Lee, Jared Isaacman, Sian Proctor, Chris Sembroski, Hayley Arceneaux | G73: 44453 | H73: 2021 | I73: TV-Y | J73: 13 min | K73: Children & Family Movies | L73: Join the StoryBots and the space travelers of the historic Inspiration4 mission as they search for answers to kids' questions about space.
A74: s73 | B74: TV Show | C74: Jack Whitehall: Travels with My Father | E74: Jack Whitehall, Michael Whitehall | F74: United Kingdom | G74: 44453 | H74: 2021 | I74: TV-MA | J74: 5 Seasons | K74: British TV Shows, Docuseries, International TV Shows | L74: Jovial comic Jack Whitehall invites his stuffy father, Michael, to travel with him through Southeast Asia in an attempt to strengthen their bond.
A75: s74 | B75: Movie | C75: King of Boys | D75: Kemi Adetiba | E75: Sola Sobowale, Adesua Etomi, Remilekun "Reminisce" Safaru, Tobechukwu "iLLbliss" Ejiofor, Toni Tones, Paul Sambo, Jide Kosoko, Sharon Ooja | F75: Nigeria | G75: 44453 | H75: 2018 | I75: TV-MA | J75: 182 min | K75: Dramas, International Movies | L75: When a powerful businesswomanâ€™s political ambitions are threatened by her underworld connections, the ensuing power struggle could cost her everything.
A76: s75 | B76: TV Show | C76: The World's Most Amazing Vacation Rentals | G76: 44453 | H76: 2021 | I76: TV-PG | J76: 2 Seasons | K76: Reality TV | L76: With an eye for every budget, three travelers visit vacation rentals around the globe and share their expert tips and tricks in this reality series.
A77: s76 | B77: Movie | C77: You vs. Wild: Out Cold | D77: Ben Simms | E77: Bear Grylls, Jason Derek Prempeh | G77: 44453 | H77: 2021 | I77: TV-G | J77: 106 min | K77: Children & Family Movies | L77: After a plane crash leaves Bear with amnesia, he must make choices to save the missing pilot and survive in this high-stakes interactive adventure.
A78: s77 | B78: TV Show | C78: Yowamushi Pedal | E78: Daiki Yamashita, Kohsuke Toriumi, Jun Fukushima, Hiroki Yasumoto, Showtaro Morikubo, Kentaro Ito, Daisuke Kishio, Yoshitsugu Matsuoka, Junichi Suwabe, Ayaka Suwa, Megumi Han, Tomoaki Maeno, Tsubasa Yonaga, Tetsuya Kakihara, Satoshi Hino, Hiroyuki Yoshino, Atsushi Abe, Koji Yusa, Kouki Miyata, Hiro Shimono, Wataru Hatano, Yuichi Nakamura, Kenji Nojima, Mamoru Miyano, Daisuke Ono, Yuma Uchida, Jun Fukuyama | F78: Japan | G78: 44453 | H78: 2013 | I78: TV-14 | J78: 1 Season | K78: Anime Series, International TV Shows | L78: A timid, anime-loving teen gets drawn into a school cycling club, where his new friends help him face tough challenges to develop his racing talent.
A79: s78 | B79: Movie | C79: Little Singham - Black Shadow | D79: Prakash Satam | E79: Sumriddhi Shukla, Jigna Bharadwaj, Sonal Kaushal, Neshma Chemburkar, Ganesh Divekar, Annamaya Verma, Anamay Verma, Manoj Pandey | G79: 44450 | H79: 2021 | I79: TV-Y7 | J79: 48 min | K79: Children & Family Movies, Comedies | L79: Kid cop Little Singham loses all his superpowers while trying to stop the demon Kaalâ€™s new evil plans! Can his inner strength help him defeat the enemy?
A80: s79 | B80: Movie | C80: Tughlaq Durbar | D80: Delhiprasad Deenadayalan | E80: Vijay Sethupathi, Parthiban, Raashi Khanna | G80: 44450 | H80: 2020 | I80: TV-14 | J80: 145 min | K80: Comedies, Dramas, International Movies | L80: A budding politician has devious plans to rise in the ranks â€” until an unexpected new presence begins to interfere with his every crooked move.
A81: s80 | B81: Movie | C81: Tughlaq Durbar (Telugu) | D81: Delhiprasad Deenadayalan | E81: Vijay Sethupathi, Parthiban, Raashi Khanna | G81: 44450 | H81: 2021 | I81: TV-14 | J81: 145 min | K81: Comedies, Dramas, International Movies | L81: A budding politician has devious plans to rise in the ranks â€” until an unexpected new presence begins to interfere with his every crooked move.
A82: s81 | B82: Movie | C82: Firedrake the Silver Dragon | D82: Tomer Eshed | E82: Thomas Brodie-Sangster, Felicity Jones, Freddie Highmore, Patrick Stewart, Meera Syal, Sanjeev Bhaskar, Nonso Anozie | G82: 44449 | H82: 2021 | I82: TV-Y7 | J82: 93 min | K82: Children & Family Movies | L82: When his home is threatened by humans, a young dragon summons the courage to seek a mythical paradise where dragons can live in peace and fly free.
A83: s82 | B83: Movie | C83: Kate | D83: Cedric Nicolas-Troyan | E83: Mary Elizabeth Winstead, Jun Kunimura, Woody Harrelson, Tadanobu Asano, Miyavi, Michiel Huisman, Miku Martineau | F83: United States | G83: 44449 | H83: 2021 | I83: R | J83: 106 min | K83: Action & Adventure | L83: Slipped a fatal poison on her final job, a ruthless assassin working in Tokyo has less than 24 hours to find out who ordered the hit and exact revenge.
A84: s83 | B84: TV Show | C84: Lucifer | E84: Tom Ellis, Lauren German, Kevin Alejandro, D.B. Woodside, Lesley-Ann Brandt, Scarlett Estevez, Rachael Harris, Aimee Garcia, Tricia Helfer, Tom Welling, Jeremiah W. Birkett, Pej Vahdat, Michael Gladis | F84: United States | G84: 44449 | H84: 2021 | I84: TV-14 | J84: 6 Seasons | K84: Crime TV Shows, TV Comedies, TV Dramas | L84: Bored with being the Lord of Hell, the devil relocates to Los Angeles, where he opens a nightclub and forms a connection with a homicide detective.
A85: s84 | B85: TV Show | C85: Metal Shop Masters | E85: Jo Koy | G85: 44449 | H85: 2021 | I85: TV-MA | J85: 1 Season | K85: Reality TV | L85: On this competition show, a group of metal artists torch, cut and weld epic, badass creations from hardened steel. Only one will win a $50,000 prize.
A86: s85 | B86: Movie | C86: Omo Ghetto: the Saga | D86: JJC Skillz, Funke Akindele | E86: Funke Akindele, Ayo Makun, Chioma Chukwuka Akpotha, Yemi Eberechi Alade, Blossom Chukwujekwu, Deyemi Okanlawon, Alexx Ekubo, Zubby Michael, Tina Mba, Femi Jacobs | F86: Nigeria | G86: 44449 | H86: 2020 | I86: TV-MA | J86: 147 min | K86: Action & Adventure, Comedies, Dramas | L86: Twins are reunited as a good-hearted female gangster and her uptight rich sister take on family, crime, cops and all of the trouble that follows them.
A87: s86 | B87: TV Show | C87: PokÃ©mon Master Journeys: The Series | E87: Ikue Otani, Sarah Natochenny, Zeno Robinson, Cherami Leigh, James Carter Cathcart, Michele Knotz, Rodger Parsons, Ray Chase, Casey Mongillo, Tara Sands | G87: 44449 | H87: 2021 | I87: TV-Y7 | J87: 1 Season | K87: Anime Series, Kids' TV | L87: As Ash battles his way through the World Coronation Series, Goh continues his quest to catch every PokÃ©mon. Together, they're on a journey to adventure!
A88: s87 | B88: Movie | C88: Prey | D88: Thomas Sieben | E88: David Kross, Hanno Koffler, Maria Ehrich, Robert Finster, Yung Ngo, Klaus Steinbacher, Livia Matthes, Nellie Thalbach | G88: 44449 | H88: 2021 | I88: TV-MA | J88: 87 min | K88: International Movies, Thrillers | L88: A hiking trip into the wild turns into a desperate bid for survival for five friends on the run from a mysterious shooter.
A89: s88 | B89: TV Show | C89: Titipo Titipo | E89: Jeon Hae-ri, Kim Eun-ah, Hong Bum-ki, Nam Do-hyeong, Um Sang-hyun | G89: 44449 | H89: 2019 | I89: TV-Y | J89: 2 Seasons | K89: Kids' TV, Korean TV Shows | L89: Titipo the train is out to prove that he's got what it takes to help the folks of Train Village ride the rails safely and reliably.
A90: s89 | B90: Movie | C90: Blood Brothers: Malcolm X & Muhammad Ali | D90: Marcus Clarke | E90: Malcolm X, Muhammad Ali | G90: 44448 | H90: 2021 | I90: PG-13 | J90: 96 min | K90: Documentaries, Sports Movies | L90: From a chance meeting to a tragic fallout, Malcolm X and Muhammad Ali's extraordinary bond cracks under the weight of distrust and shifting ideals.
A91: s90 | B91: TV Show | C91: Mighty Raju | E91: Julie Tejwani, Sabina Malik, Jigna Bhardwaj, Rupa Bhimani, Lalit Agarwal, Rajesh Shukla, Rajesh Kava | G91: 44448 | H91: 2017 | I91: TV-Y7 | J91: 4 Seasons | K91: Kids' TV | L91: Born with superhuman abilities, young Raju wants to use his powers to make the world a better place â€” but that will mean facing plenty of challenges!
A92: s91 | B92: Movie | C92: Paradise Hills | D92: Alice Waddington | E92: Emma Roberts, Danielle Macdonald, Awkwafina, Eiza GonzÃ¡lez, Milla Jovovich, Jeremy Irvine, Arnaud Valois, Daniel Horvath | F92: Spain, United States | G92: 44448 | H92: 2019 | I92: TV-MA | J92: 95 min | K92: Sci-Fi & Fantasy, Thrillers | L92: Uma wakes up in a lush tropical facility designed to turn willful girls into perfect ladies. Thatâ€™s bad enough, but its real purpose is even worse.
A93: s92 | B93: Movie | C93: The Women and the Murderer | D93: Mona Achache, Patricia Tourancheau | F93: France | G93: 44448 | H93: 2021 | I93: TV-14 | J93: 92 min | K93: Documentaries, International Movies | L93: This documentary traces the capture of serial killer Guy Georges through the tireless work of two women: a police chief and a victim's mother.
A94: s93 | B94: TV Show | C94: Into the Night | E94: Pauline Etienne, Laurent Capelluto, Stefano Cassetti, Mehmet KurtuluÅŸ, Babetida Sadjo, Jan Bijvoet, Ksawery Szlenkier, Vincent Londez, Regina Bikkinina, Alba GaÃ¯a Kraghede Bellugi, Nabil Mallat | F94: Belgium | G94: 44447 | H94: 2021 | I94: TV-MA | J94: 2 Seasons | K94: International TV Shows, TV Dramas, TV Mysteries | L94: Passengers and crew aboard a hijacked overnight flight scramble to outrace the sun as a mysterious cosmic event wreaks havoc on the world below.
A95: s94 | B95: Movie | C95: JJ+E | D95: Alexis AlmstrÃ¶m | E95: Elsa Ã–hrn, Mustapha Aarab, Jonay Pineda Skallak, Magnus Krepper, Loreen, Albin Grenholm, Simon Mezher, Elsa BergstrÃ¶m Terent, Josef Kadim, Yohannes Frezgi | G95: 44447 | H95: 2021 | I95: TV-MA | J95: 91 min | K95: Dramas, International Movies, Romantic Movies | L95: Elisabeth and John-John live in the same city, but they inhabit different worlds. Can a passionate first love break through class and cultural barriers?
A96: s95 | B96: Movie | C96: Show Dogs | D96: Raja Gosnell | E96: Will Arnett, Ludacris, Natasha Lyonne, Stanley Tucci, Jordin Sparks, Gabriel Iglesias, Shaquille O'Neal, Omar Chaparro, Alan Cumming, Andy Beckwith, Delia Sheppard, Kerry Shale | F96: United Kingdom, United States | G96: 44447 | H96: 2018 | I96: PG | J96: 90 min | K96: Children & Family Movies, Comedies | L96: A rough and tough police dog must go undercover with an FBI agent as a prim and proper pet at a dog show to save a baby panda from an illegal sale.
A97: s96 | B97: TV Show | C97: The Circle | E97: Michelle Buteau | F97: United States, United Kingdom | G97: 44447 | H97: 2021 | I97: TV-MA | J97: 3 Seasons | K97: Reality TV | L97: Status and strategy collide in this social experiment and competition show where online players flirt, befriend and catfish their way toward $100,000.
A98: s97 | B98: Movie | C98: If I Leave Here Tomorrow: A Film About Lynyrd Skynyrd | D98: Stephen Kijak | E98: Ronnie Van Zandt, Gary Rossington, Allen Collins, Leon Wilkeson, Bob Burns, Billy Powell, Ed King, Artimus Pyle, Steve Gaines, Johnny Van Zant | F98: United States | G98: 44446 | H98: 2018 | I98: TV-MA | J98: 97 min | K98: Documentaries, Music & Musicals | L98: Using interviews and archival footage, this documentary charts the story of the legendary Southern rockers with a focus on front man Ronnie Van Zant.
A99: s98 | B99: TV Show | C99: Kid Cosmic | E99: Jack Fisher, Tom Kenny, Amanda C. Miller, Kim Yarbrough, Keith Ferguson, Grey Griffin, Lily Rose Silver | F99: United States | G99: 44446 | H99: 2021 | I99: TV-Y7 | J99: 2 Seasons | K99: Kids' TV, TV Comedies, TV Sci-Fi & Fantasy | L99: A boy's superhero dreams come true when he finds five powerful cosmic stones. But saving the day is harder than he imagined â€” and he can't do it alone.
A100: s99 | B100: TV Show | C100: Octonauts: Above & Beyond | E100: Antonio Aakeel, Chipo Chung, Simon Foster, Teresa Gallagher, Simon Greenall, Kate Harbour, Paul Panting, Rob Rackstraw, William Vanderpuye, Helen Walsh, Keith Wickham, Andres Williams, Jo Wyatt | F100: United Kingdom | G100: 44446 | H100: 2021 | I100: TV-Y | J100: 1 Season | K100: British TV Shows, Kids' TV | L100: The Octonauts expand their exploration beyond the sea â€”Â and onto land! With new rides and new friends, they'll protect any habitats and animals at risk.
...

Sheet Financials
A1: Quarter | B1: Region | C1: Revenue_USD_Millions | D1: YoY_Growth_Percent | E1: Source | F1: Source_Date | G1: Notes
A2: Q1 2024 | B2: UCAN | C2: 4224 | D2: 17 | E2: Netflix Q1 2024 Shareholder Letter | F2: 45400 | G2: Reported in millions
A3: Q1 2024 | B3: EMEA | C3: 2958 | D3: 17 | E3: Netflix Q1 2024 Shareholder Letter | F3: 45400 | G3: Reported in millions
A4: Q1 2024 | B4: LATAM | C4: 1165 | D4: 9 | E4: Netflix Q1 2024 Shareholder Letter | F4: 45400 | G4: Reported in millions
A5: Q1 2024 | B5: APAC | C5: 1023 | D5: 10 | E5: Netflix Q1 2024 Shareholder Letter | F5: 45400 | G5: Reported in millions
A6: Q2 2024 | B6: UCAN | C6: 4296 | D6: 19 | E6: Netflix Q2 2024 Shareholder Letter | F6: 45491 | G6: Reported in millions
A7: Q2 2024 | B7: EMEA | C7: 3008 | D7: 17 | E7: Netflix Q2 2024 Shareholder Letter | F7: 45491 | G7: Reported in millions
A8: Q2 2024 | B8: LATAM | C8: 1204 | D8: 12 | E8: Netflix Q2 2024 Shareholder Letter | F8: 45491 | G8: Reported in millions
A9: Q2 2024 | B9: APAC | C9: 1052 | D9: 14 | E9: Netflix Q2 2024 Shareholder Letter | F9: 45491 | G9: Reported in millions
A10: Q3 2024 | B10: UCAN | C10: 4322 | D10: 16 | E10: Netflix Q3 2024 Shareholder Letter | F10: 45582 | G10: Reported in millions
A11: Q3 2024 | B11: EMEA | C11: 3133 | D11: 16 | E11: Netflix Q3 2024 Shareholder Letter | F11: 45582 | G11: Reported in millions
A12: Q3 2024 | B12: LATAM | C12: 1241 | D12: 9 | E12: Netflix Q3 2024 Shareholder Letter | F12: 45582 | G12: Reported in millions
A13: Q3 2024 | B13: APAC | C13: 1128 | D13: 19 | E13: Netflix Q3 2024 Shareholder Letter | F13: 45582 | G13: Reported in millions
... A37: Q1 2026 | B37: APAC | C37: 1509 | D37: 20 | E37: FINAL-Q1-26-Shareholder-Letter.pdf | F37: 46128 | G37: Reported in millions

Sheet Analysis
A1: Regional Revenue Summary | C1: Region | D1: UCAN | E1: EMEA | F1: LATAM | G1: APAC
C2: Latest Revenue | D2: =SUMIFS(Table2[Revenue_USD_Millions],Table2[Region],Analysis!D1,Table2[Quarter],Financials!A34) -> 5245 | E2: =SUMIFS(Table2[Revenue_USD_Millions],Table2[Region],Analysis!E1,Table2[Quarter],Financials!A34) -> 3998 | F2: =SUMIFS(Table2[Revenue_USD_Millions],Table2[Region],Analysis!F1,Table2[Quarter],Financials!A34) -> 1497 | G2: =SUMIFS(Table2[Revenue_USD_Millions],Table2[Region],Analysis!G1,Table2[Quarter],Financials!A34) -> 1509 | X2: Region | Y2: Q4 2025 Revenue | Z2: Q1 2026 Revenue | AA2: Revenue Change | AB2: Revenue Change percentage
C3: Previous revenue | D3: =SUMIFS(Table2[Revenue_USD_Millions],Table2[Region],Analysis!D1,Table2[Quarter],Financials!A33) -> 5339 | E3: =SUMIFS(Table2[Revenue_USD_Millions],Table2[Region],Analysis!E1,Table2[Quarter],Financials!A33) -> 3873 | F3: =SUMIFS(Table2[Revenue_USD_Millions],Table2[Region],Analysis!F1,Table2[Quarter],Financials!A33) -> 1418 | G3: =SUMIFS(Table2[Revenue_USD_Millions],Table2[Region],Analysis!G1,Table2[Quarter],Financials!A33) -> 1421 | X3: UCAN | Y3: 5339 | Z3: 5245 | AA3: -94 | AB3: =(Z3-Y3)/Y3 -> -0.017606293
C4: Revenue Change | D4: =D2-D3 -> -94 | E4: =E2-E3 -> 125 | F4: =F2-F3 -> 79 | G4: =G2-G3 -> 88 | X4: EMEA | Y4: 3873 | Z4: 3998 | AA4: 125 | AB4: =(Z4-Y4)/Y4 -> 0.032274722
X5: LATAM | Y5: 1418 | Z5: 1497 | AA5: 79 | AB5: =(Z5-Y5)/Y5 -> 0.055712271
C6: Revenue change percentage | D6: =D4/D3 -> -0.017606293 | E6: =E4/E3 -> 0.032274722 | F6: =F4/F3 -> 0.055712271 | G6: =G4/G3 -> 0.06192822 | X6: APAC | Y6: 1421 | Z6: 1509 | AA6: 88 | AB6: =(Z6-Y6)/Y6 -> 0.06192822
X7: Netflix Quarterly Revenue Trends (Q4 2025–Q1 2026).
C9: Quater | D9: UCAN | E9: EMEA | F9: LATAM | G9: APAC | H9: Total Revenue | I9: Quarter Over Quarter Revenue Growth
C10: Q1 2024 | D10: =SUMIFS(Table2[Revenue_USD_Millions],Table2[Region],D$9,Table2[Quarter],$C10) -> 4224 | E10: =SUMIFS(Table2[Revenue_USD_Millions],Table2[Region],E$9,Table2[Quarter],$C10) -> 2958 | F10: =SUMIFS(Table2[Revenue_USD_Millions],Table2[Region],F$9,Table2[Quarter],$C10) -> 1165 | G10: =SUMIFS(Table2[Revenue_USD_Millions],Table2[Region],G$9,Table2[Quarter],$C10) -> 1023 | H10: =SUM(D10:G10) -> 9370 | X10: Region | Y10: Q1 2024 Revenue | Z10: Q1 2026 Revenue | AA10: Revenue Change | AB10: Revenue Growth (%)
C11: Q2 2024 | D11: =SUMIFS(Table2[Revenue_USD_Millions],Table2[Region],D$9,Table2[Quarter],$C11) -> 4296 | E11: =SUMIFS(Table2[Revenue_USD_Millions],Table2[Region],E$9,Table2[Quarter],$C11) -> 3008 | F11: =SUMIFS(Table2[Revenue_USD_Millions],Table2[Region],F$9,Table2[Quarter],$C11) -> 1204 | G11: =SUMIFS(Table2[Revenue_USD_Millions],Table2[Region],G$9,Table2[Quarter],$C11) -> 1052 | H11: =SUM(D11:G11) -> 9560 | I11: =(H11-H10)/H10 -> 0.020277481 | X11: UCAN | Y11: 4224 | Z11: 5245 | AA11: =Z11-Y11 -> 1021 | AB11: =(Z11-Y11)/Y11 -> 0.24171402
C12: Q3 2024 | D12: =SUMIFS(Table2[Revenue_USD_Millions],Table2[Region],D$9,Table2[Quarter],$C12) -> 4322 | E12: =SUMIFS(Table2[Revenue_USD_Millions],Table2[Region],E$9,Table2[Quarter],$C12) -> 3133 | F12: =SUMIFS(Table2[Revenue_USD_Millions],Table2[Region],F$9,Table2[Quarter],$C12) -> 1241 | G12: =SUMIFS(Table2[Revenue_USD_Millions],Table2[Region],G$9,Table2[Quarter],$C12) -> 1128 | H12: =SUM(D12:G12) -> 9824 | I12: =(H12-H11)/H11 -> 0.027615063 | X12: EMEA | Y12: 2958 | Z12: 3998 | AA12: =Z12-Y12 -> 1040 | AB12: =(Z12-Y12)/Y12 -> 0.35158891
C13: Q4 2024 | D13: =SUMIFS(Table2[Revenue_USD_Millions],Table2[Region],D$9,Table2[Quarter],$C13) -> 4517 | E13: =SUMIFS(Table2[Revenue_USD_Millions],Table2[Region],E$9,Table2[Quarter],$C13) -> 3288 | F13: =SUMIFS(Table2[Revenue_USD_Millions],Table2[Region],F$9,Table2[Quarter],$C13) -> 1230 | G13: =SUMIFS(Table2[Revenue_USD_Millions],Table2[Region],G$9,Table2[Quarter],$C13) -> 1212 | H13: =SUM(D13:G13) -> 10247 | I13: =(H13-H12)/H12 -> 0.043057818 | X13: LATAM | Y13: 1165 | Z13: 1497 | AA13: =Z13-Y13 -> 332 | AB13: =(Z13-Y13)/Y13 -> 0.28497854
C14: Q1 2025 | D14: =SUMIFS(Table2[Revenue_USD_Millions],Table2[Region],D$9,Table2[Quarter],$C14) -> 4617 | E14: =SUMIFS(Table2[Revenue_USD_Millions],Table2[Region],E$9,Table2[Quarter],$C14) -> 3405 | F14: =SUMIFS(Table2[Revenue_USD_Millions],Table2[Region],F$9,Table2[Quarter],$C14) -> 1262 | G14: =SUMIFS(Table2[Revenue_USD_Millions],Table2[Region],G$9,Table2[Quarter],$C14) -> 1259 | H14: =SUM(D14:G14) -> 10543 | I14: =(H14-H13)/H13 -> 0.028886503 | X14: APAC | Y14: 1023 | Z14: 1509 | AA14: =Z14-Y14 -> 486 | AB14: =(Z14-Y14)/Y14 -> 0.47507331
C15: Q2 2025 | D15: =SUMIFS(Table2[Revenue_USD_Millions],Table2[Region],D$9,Table2[Quarter],$C15) -> 4929 | E15: =SUMIFS(Table2[Revenue_USD_Millions],Table2[Region],E$9,Table2[Quarter],$C15) -> 3538 | F15: =SUMIFS(Table2[Revenue_USD_Millions],Table2[Region],F$9,Table2[Quarter],$C15) -> 1307 | G15: =SUMIFS(Table2[Revenue_USD_Millions],Table2[Region],G$9,Table2[Quarter],$C15) -> 1305 | H15: =SUM(D15:G15) -> 11079 | I15: =(H15-H14)/H14 -> 0.05083942 | X15: Netflix Quarterly Revenue Trends (Q1 2024–Q1 2026).
C16: Q3 2025 | D16: =SUMIFS(Table2[Revenue_USD_Millions],Table2[Region],D$9,Table2[Quarter],$C16) -> 5072 | E16: =SUMIFS(Table2[Revenue_USD_Millions],Table2[Region],E$9,Table2[Quarter],$C16) -> 3699 | F16: =SUMIFS(Table2[Revenue_USD_Millions],Table2[Region],F$9,Table2[Quarter],$C16) -> 1371 | G16: =SUMIFS(Table2[Revenue_USD_Millions],Table2[Region],G$9,Table2[Quarter],$C16) -> 1369 | H16: =SUM(D16:G16) -> 11511 | I16: =(H16-H15)/H15 -> 0.038992689
C17: Q4 2025 | D17: =SUMIFS(Table2[Revenue_USD_Millions],Table2[Region],D$9,Table2[Quarter],$C17) -> 5339 | E17: =SUMIFS(Table2[Revenue_USD_Millions],Table2[Region],E$9,Table2[Quarter],$C17) -> 3873 | F17: =SUMIFS(Table2[Revenue_USD_Millions],Table2[Region],F$9,Table2[Quarter],$C17) -> 1418 | G17: =SUMIFS(Table2[Revenue_USD_Millions],Table2[Region],G$9,Table2[Quarter],$C17) -> 1421 | H17: =SUM(D17:G17) -> 12051 | I17: =(H17-H16)/H16 -> 0.04691165
C18: Q1 2026 | D18: =SUMIFS(Table2[Revenue_USD_Millions],Table2[Region],D$9,Table2[Quarter],$C18) -> 5245 | E18: =SUMIFS(Table2[Revenue_USD_Millions],Table2[Region],E$9,Table2[Quarter],$C18) -> 3998 | F18: =SUMIFS(Table2[Revenue_USD_Millions],Table2[Region],F$9,Table2[Quarter],$C18) -> 1497 | G18: =SUMIFS(Table2[Revenue_USD_Millions],Table2[Region],G$9,Table2[Quarter],$C18) -> 1509 | H18: =SUM(D18:G18) -> 12249 | I18: =(H18-H17)/H17 -> 0.016430172 | AE18: Key Findings
E20: Netflix Revenue for each Quarter | AE20: 1. APAC recorded the highest full-period revenue growth at 48% from Q1 2024 to Q1 2026.
AE22: 2. EMEA revenue grew by 35%, while LATAM grew by 28% over the same period.
N24: Line Graph for Revenue of each Quarter | AE24: 3. UCAN revenue grew by 24% over the full period, but declined by 1.76% from Q4 2025 to Q1 2026.
AE26: 4. APAC had the highest quarter-over-quarter regional revenue growth from Q4 2025 to Q1 2026, at 6.19%.

Sheet Dashboard
A1: NETFLIX | GROWTH & REVENUE DASHBOARD
A4: Where Should Netflix Invest for Its Next Phase of Growth?
A7: LATEST QUARTER REVENUE | E7: TOP REGION GROWTH
A8: =SUM(Analysis!D18:G18) -> 12249 | E8: =MAX(Analysis!AB11:AB14) -> 0.47507331
A38: KEY INSIGHTS
A40: APAC recorded the strongest regional revenue growth over the period, increasing by approximately 48% from Q1 2024 to Q1 2026.
A41: EMEA revenue grew by approximately 35%, while LATAM grew by approximately 28% over the same period.
A42: UCAN revenue increased by approximately 24% over the full period but declined from Q4 2025 to Q1 2026.
A43: APAC had the highest quarter-over-quarter regional revenue growth in Q1 2026, at approximately 6.2%.

Sheet Recommendation
A1: NETFLIX | STRATEGIC GROWTH RECOMMENDATIONS
A2: Where should Netflix focus its next phase of regional growth?
A6: Priority | B6: Region | C6: Key finding | D6: Recomendation | E6: Expected Impact
A7: High | B7: APAC | C7: Strongest full-period regional growth at approximately 48% and strongest Q1 2026 QoQ growth at approximately 6.2%. | D7: Prioritize investment in APAC through localized content, market-specific engagement strategies, and continued subscriber growth initiatives. | E7: Sustain the strongest regional growth trajectory and increase APAC's contribution to overall revenue.
A8: High | B8: EMEA | C8: Revenue increased by approximately 35% from Q1 2024 to Q1 2026, with continued growth in Q1 2026. | D8: Continue investing in regional content and strengthen successful markets while identifying additional opportunities for expansion. | E8: Maintain steady growth and strengthen EMEA as a major contributor to Netflix revenue.
A9: Monitor | B9: UCAN | C9: UCAN grew approximately 24% over the full period but declined approximately 1.8% from Q4 2025 to Q1 2026. | D9: Focus on retention, engagement, and content effectiveness rather than relying primarily on expansion. | E9: Reduce the risk of further regional slowdown and protect Netflix's largest revenue base.
A10: Evaluate | B10: LATAM | C10: Revenue grew approximately 28% from Q1 2024 to Q1 2026, with approximately 5.6% QoQ growth in Q1 2026. | D10: Evaluate opportunities to expand localized content and strengthen engagement, prioritizing initiatives supported by market-level evidence. | E10: Identify sustainable growth opportunities and improve LATAM's contribution to overall revenue.
A12: KEY INSIGHTS
A14: Netflix should prioritize APAC for incremental growth investment, maintain EMEA's momentum, and focus on protecting and re-energizing UCAN through stronger retention and engagement strategies.
C18: Region | D18: Full Period Growth
C19: APAC | D19: =Analysis!AB14 -> 0.47507331
C20: EMEA | D20: =Analysis!AB12 -> 0.35158891
C21: UCAN | D21: =Analysis!AB11 -> 0.24171402
C22: LATAM | D22: =Analysis!AB13 -> 0.28497854

Sheet Memberships and ARM
A1: Quarter | B1: Region | C1: Paid_Memberships_Millions | D1: ARM_USD | E1: Source | F1: Source_Date | G1: Notes
A2: Q1 2024 | B2: UCAN | C2: 82.66 | D2: 17.3 | E2: Netflix Q1 2024 Shareholder Letter | F2: 45400 | G2: Paid memberships and ARM reported
A3: Q1 2024 | B3: EMEA | C3: 91.73 | D3: 10.92 | E3: Netflix Q1 2024 Shareholder Letter | F3: 45400 | G3: Paid memberships and ARM reported
A4: Q1 2024 | B4: LATAM | C4: 47.72 | D4: 8.29 | E4: Netflix Q1 2024 Shareholder Letter | F4: 45400 | G4: Paid memberships and ARM reported
A5: Q1 2024 | B5: APAC | C5: 47.5 | D5: 7.35 | E5: Netflix Q1 2024 Shareholder Letter | F5: 45400 | G5: Paid memberships and ARM reported
A6: Q2 2024 | B6: UCAN | C6: 84.11 | D6: 17.17 | E6: Netflix Q2 2024 Shareholder Letter | F6: 45491 | G6: Paid memberships and ARM reported
A7: Q2 2024 | B7: EMEA | C7: 93.96 | D7: 10.8 | E7: Netflix Q2 2024 Shareholder Letter | F7: 45491 | G7: Paid memberships and ARM reported
A8: Q2 2024 | B8: LATAM | C8: 49.25 | D8: 8.28 | E8: Netflix Q2 2024 Shareholder Letter | F8: 45491 | G8: Paid memberships and ARM reported
A9: Q2 2024 | B9: APAC | C9: 50.32 | D9: 7.17 | E9: Netflix Q2 2024 Shareholder Letter | F9: 45491 | G9: Paid memberships and ARM reported
A10: Q3 2024 | B10: UCAN | C10: 84.8 | D10: 17.06 | E10: Netflix Q3 2024 Shareholder Letter | F10: 45582 | G10: Paid memberships and ARM reported
A11: Q3 2024 | B11: EMEA | C11: 96.13 | D11: 10.99 | E11: Netflix Q3 2024 Shareholder Letter | F11: 45582 | G11: Paid memberships and ARM reported
A12: Q3 2024 | B12: LATAM | C12: 49.18 | D12: 8.4 | E12: Netflix Q3 2024 Shareholder Letter | F12: 45582 | G12: Paid memberships and ARM reported
A13: Q3 2024 | B13: APAC | C13: 52.6 | D13: 7.31 | E13: Netflix Q3 2024 Shareholder Letter | F13: 45582 | G13: Paid memberships and ARM reported
... A17: Q4 2024 | B17: APAC | C17: 57.54 | D17: 7.34 | E17: Netflix Q4 2024 Shareholder Letter | F17: 45678 | G17: Paid memberships and ARM reported
A18: Q1 2025 | B18: UCAN | E18: Netflix Q1 2025 Shareholder Letter | F18: 45764 | G18: Memberships and ARM not reported
A19: Q1 2025 | B19: EMEA | E19: Netflix Q1 2025 Shareholder Letter | F19: 45764 | G19: Memberships and ARM not reported
A20: Q1 2025 | B20: LATAM | E20: Netflix Q1 2025 Shareholder Letter | F20: 45764 | G20: Memberships and ARM not reported
A21: Q1 2025 | B21: APAC | E21: Netflix Q1 2025 Shareholder Letter | F21: 45764 | G21: Memberships and ARM not reported

Sheet Source log
A1: Quarter | B1: Document_Title | C1: Publication_Date | D1: Data_Extracted | E1: Limitations
A2: Q1 2024 | B2: Netflix Q1 2024 Shareholder Letter | C2: 45400 | D2: Regional revenue, YoY growth, paid memberships, ARM | E2: None noted in supplied data
A3: Q2 2024 | B3: Netflix Q2 2024 Shareholder Letter | C3: 45491 | D3: Regional revenue, YoY growth, paid memberships, ARM | E3: None noted in supplied data
A4: Q3 2024 | B4: Netflix Q3 2024 Shareholder Letter | C4: 45582 | D4: Regional revenue, YoY growth, paid memberships, ARM | E4: None noted in supplied data
A5: Q4 2024 | B5: Netflix Q4 2024 Shareholder Letter | C5: 45678 | D5: Regional revenue, YoY growth, paid memberships, ARM | E5: None noted in supplied data
A6: Q1 2025 | B6: Netflix Q1 2025 Shareholder Letter | C6: 45764 | D6: Regional revenue, YoY growth | E6: Paid memberships and ARM not reported
A7: Q2 2025 | B7: Netflix Q2 2025 Shareholder Letter | C7: 45855 | D7: Regional revenue, YoY growth | E7: Paid memberships and ARM not reported
A8: Q3 2025 | B8: Netflix Q3 2025 Shareholder Letter | C8: 45951 | D8: Regional revenue, YoY growth | E8: Paid memberships and ARM not reported
A9: Q4 2025 | B9: FINAL-Q4-25-Shareholder-Letter.pdf | C9: 46042 | D9: Regional revenue, YoY growth | E9: Paid memberships and ARM not reported
A10: Q1 2026 | B10: FINAL-Q1-26-Shareholder-Letter.pdf | C10: 46128 | D10: Regional revenue, YoY growth | E10: Paid memberships and ARM not reported
